{
"type": "FeatureCollection",
"name": "network_based_walk_points",
"crs": { "type": "name", "properties": { "name": "urn:ogc:def:crs:OGC:1.3:CRS84" } },
"features": [
{ "type": "Feature", "properties": { }, "geometry": { "type": "Point", "coordinates": [ 3.4597277, 6.452619 ] } }
]
}
